MANIFEST.in
setup.py
QCloudChameleon.egg-info/PKG-INFO
QCloudChameleon.egg-info/SOURCES.txt
QCloudChameleon.egg-info/dependency_links.txt
QCloudChameleon.egg-info/requires.txt
QCloudChameleon.egg-info/top_level.txt
bin/chameleon
chameleon/__init__.py
chameleon/core/__init__.py
chameleon/core/codegen/__init__.py
chameleon/core/codegen/model.py
chameleon/core/codegen/property.py
chameleon/core/codegen/request.py
chameleon/core/codegen/android/__init__.py
chameleon/core/codegen/android/adgenerator.py
chameleon/core/codegen/oc/__init__.py
chameleon/core/codegen/oc/generate.py
chameleon/core/config/__init__.py
chameleon/core/config/config.py
chameleon/core/engine/ChameleonLexer.py
chameleon/core/engine/ChameleonListener.py
chameleon/core/engine/ChameleonParser.py
chameleon/core/engine/__init__.py
chameleon/core/parser/__init__.py
chameleon/core/parser/listener.py
chameleon/core/resources/template/android/model/model.clout
chameleon/core/resources/template/android/request/model.clout
chameleon/core/resources/template/oc/bwmodel/model_header.clout
chameleon/core/resources/template/oc/bwmodel/model_implatation.clout
chameleon/core/resources/template/oc/dic/BWDeepCopy.h
chameleon/core/resources/template/oc/dic/BWDeepCopy.m
chameleon/core/resources/template/oc/dic/BWDeepCopyProtocol.h
chameleon/core/resources/template/oc/dic/BWModelProtocol.h
chameleon/core/resources/template/oc/dic/BWTODictionary.h
chameleon/core/resources/template/oc/dic/BWTODictionary.m
chameleon/core/resources/template/oc/dic/EnsureType.h
chameleon/core/resources/template/oc/dic/EnsureType.m
chameleon/core/resources/template/oc/dic/NSObject+DeepCopy.h
chameleon/core/resources/template/oc/dic/NSObject+DeepCopy.m
chameleon/core/resources/template/oc/dic/NSObject+TODictionary.h
chameleon/core/resources/template/oc/dic/NSObject+TODictionary.m
chameleon/core/resources/template/oc/dic/model_header.clout
chameleon/core/resources/template/oc/dic/model_implatation.clout
chameleon/core/resources/template/oc/mantle/model_header.clout
chameleon/core/resources/template/oc/mantle/model_implatation.clout
chameleon/core/resources/template/oc/request/model_header.clout
