Metadata-Version: 1.0
Name: QCloudChameleon
Version: 0.1.0
Summary: a DSL tool to generate Objective-C model code
Home-page: http://www.github.com/yishuiliunian
Author: yishuiliunian
Author-email: yishuiliunian@gmail.com
License: GPL
Keywords: Objective-C,DSL,model
Platform: any
